pynopticon/__init__.py
pynopticon/mailer.py
pynopticon/server.py
pynopticon/upload_video.py
Pynopticon-0.0.8.dist-info/LICENSE
Pynopticon-0.0.8.dist-info/METADATA
Pynopticon-0.0.8.dist-info/WHEEL
Pynopticon-0.0.8.dist-info/entry_points.txt
Pynopticon-0.0.8.dist-info/top_level.txt
Pynopticon-0.0.8.dist-info/RECORD
