Metadata-Version: 2.1
Name: Pynopticon
Version: 0.0.8
Summary: Pynopticon
Home-page: https://www.github.com/rickwierenga/pynopticon/
Author: Rick Wierenga
Author-email: rick_wierenga@icloud.com
License-File: LICENSE
Requires-Dist: opencv-python
Provides-Extra: mail
Requires-Dist: sendgrid ; extra == 'mail'
Provides-Extra: server
Requires-Dist: flask ; extra == 'server'
Provides-Extra: yt
Requires-Dist: google-api-python-client ; extra == 'yt'
Requires-Dist: apiclient ; extra == 'yt'
Requires-Dist: httplib2 ; extra == 'yt'
Requires-Dist: oauth2client ; extra == 'yt'
